xlsxq/__init__.py
xlsxq-0.1.3.dist-info/entry_points.txt
xlsxq-0.1.3.dist-info/LICENSE
xlsxq-0.1.3.dist-info/WHEEL
xlsxq-0.1.3.dist-info/METADATA
xlsxq-0.1.3.dist-info/RECORD
