Metadata-Version: 2.1
Name: xlsxq
Version: 0.1.3
Summary: xlsxq is a lightweight and flexible command-line .xlsx processor.
Home-page: https://github.com/kumarstack55/xlsxq
License: MIT
Author: kumarstack55
Author-email: kumarstack55@gmail.com
Requires-Python: >=3.8,<4.0
Classifier: Development Status :: 4 - Beta
Classifier: License :: OSI Approved :: MIT License
Classifier: Programming Language :: Python :: 3
Classifier: Programming Language :: Python :: 3.10
Classifier: Programming Language :: Python :: 3.8
Classifier: Programming Language :: Python :: 3.9
Classifier: Topic :: Office/Business :: Financial :: Spreadsheet
Requires-Dist: openpyxl (>=3.0.9,<4.0.0)
Project-URL: Documentation, https://github.com/kumarstack55/xlsxq
Project-URL: Repository, https://github.com/kumarstack55/xlsxq
